pireplay/__init__.py
pireplay/camera.py
pireplay/cli.py
pireplay/config.py
pireplay/consts.py
pireplay/default_config.yaml
pireplay/network.py
pireplay/replays.py
pireplay/static/base.css
pireplay/static/favicon.png
pireplay/static/fonts/FiraCode-Regular.ttf
pireplay/static/fonts/FiraCode-SemiBold.ttf
pireplay/static/fonts/OFL.txt
pireplay/static/style.css
pireplay/templates/base.html
pireplay/templates/components/nav.html
pireplay/templates/index.html
pireplay/templates/network.html
pireplay/templates/replay.html
pireplay/templates/settings.html
pireplay/web_server.py
pireplay-0.1.0.dist-info/METADATA
pireplay-0.1.0.dist-info/WHEEL
pireplay-0.1.0.dist-info/entry_points.txt
pireplay-0.1.0.dist-info/RECORD
